{
  "HVIGOR_OHOS_PLUGIN": {
    "MODULES": [
      {
        "MODULE_NAME": "923fe53966c6cd9343e11af776cd4b05be315ea4b200b02e4d5dfb0f929b73bf",
        "API_TYPE": "stageMode"
      }
    ],
    "NATIVE_COMPILER": "Default",
    "BUILD_MODE": "debug"
  },
  "HVIGOR": {
    "IS_INCREMENTAL": true,
    "IS_DAEMON": true,
    "IS_PARALLEL": true,
    "IS_HVIGORFILE_TYPE_CHECK": false,
    "TASK_TIME": {
      "923fe53966c6cd9343e11af776cd4b05be315ea4b200b02e4d5dfb0f929b73bf": {
        "CreateModuleInfo": 413500,
        "PreCheckSyscap": 185200,
        "GeneratePkgContextInfo": 2516900,
        "ProcessStartupConfig": 553700,
        "PreviewProcessResource": 834300,
        "PreviewCompileResource": 493012500,
        "PreviewHookCompileResource": 180900,
        "CopyPreviewProfile": 4165800,
        "ReplacePreviewerPage": 307300,
        "buildPreviewerResource": 121500,
        "PreviewUpdateAssets": 1889900,
        "PreviewArkTS": 4863373600,
        "PreviewBuild": 180800
      }
    },
    "APIS": [
      "getHvigorConfig",
      "getRootNodeDescriptor",
      "getChildNode",
      "getNodeByName",
      "getAllNodes",
      "getRootNode",
      "getNodeName",
      "getNodePath",
      "subNodes",
      "getExtraOption",
      "getExtParam",
      "getExtParams",
      "getProperty",
      "getProperties",
      "getProductName",
      "nodesEvaluated",
      "getParameter",
      "getCommandEntryTask",
      "getStartParams"
    ],
    "CONFIG_PROPERTIES": {},
    "TOTAL_TIME": 5494618500,
    "BUILD_ID": "202601040203162140"
  }
}